candfans_client/__init__.py
candfans_client/async_client.py
candfans_client/client.py
candfans_client/exceptions.py
candfans_client/models/__init__.py
candfans_client/models/sales.py
candfans_client/models/search.py
candfans_client/models/timeline.py
candfans_client/models/user.py
candfans_client-3.8.1.dist-info/LICENSE
candfans_client-3.8.1.dist-info/METADATA
candfans_client-3.8.1.dist-info/WHEEL
candfans_client-3.8.1.dist-info/RECORD
