Metadata-Version: 2.3
Name: candfans-client
Version: 3.8.1
Summary: 
License: MIT
Keywords: API
Author: komanushi
Requires-Python: >=3.9,<4.0
Classifier: License :: OSI Approved :: MIT License
Classifier: Programming Language :: Python :: 3
Classifier: Programming Language :: Python :: 3.9
Classifier: Programming Language :: Python :: 3.10
Classifier: Programming Language :: Python :: 3.11
Classifier: Programming Language :: Python :: 3.12
Classifier: Programming Language :: Python :: 3.13
Requires-Dist: httpx (>=0.27.0,<0.28.0)
Requires-Dist: pydantic (>=2.5.3,<3.0.0)
Requires-Dist: python-dateutil (>=2.8.2,<3.0.0)
Project-URL: Homepage, https://github.com/komanushi/candfans-client
Project-URL: Repository, https://github.com/komanushi/candfans-client
